_catdict.cp310-win_amd64.pyd
catdict/__init__.py
catdict/ext.cp310-win_amd64.pyd
catdict/include/catdict.h
catdict/include/cd_bool.h
catdict/include/cd_dict.h
catdict/include/cd_float.h
catdict/include/cd_list.h
catdict/include/cd_long.h
catdict/include/cd_set.h
catdict/include/cd_tuple.h
catdict/include/cd_unicode.h
catdict/include/dtypes.h
catdict/src/catdict.c
catdict/src/catdict_ext.c
catdict/src/catdict_module.c
catdict/src/cd_bool.c
catdict/src/cd_dict.c
catdict/src/cd_float.c
catdict/src/cd_list.c
catdict/src/cd_long.c
catdict/src/cd_set.c
catdict/src/cd_tuple.c
catdict/src/cd_unicode.c
catdict/src/dtypes.c
catdict-0.4.3.dist-info/LICENSE
catdict-0.4.3.dist-info/METADATA
catdict-0.4.3.dist-info/WHEEL
catdict-0.4.3.dist-info/top_level.txt
catdict-0.4.3.dist-info/RECORD
