Metadata-Version: 2.1
Name: catdict
Version: 0.4.3
Summary: Python package providing categorical dict class.
Home-page: https://github.com/clumsykun/catdict
Author: Zhao Kunwang
Author-email: clumsykundev@gmail.com
License: UNKNOWN
Platform: UNKNOWN
License-File: LICENSE
